stucknet/__init__.py
stucknet/stucknet.py
stucknet-1.0.1.dist-info/LICENSE
stucknet-1.0.1.dist-info/METADATA
stucknet-1.0.1.dist-info/WHEEL
stucknet-1.0.1.dist-info/top_level.txt
stucknet-1.0.1.dist-info/RECORD
