Metadata-Version: 2.1
Name: stucknet
Version: 1.0.1
Summary: A flawlessly secured vault!
Author-email: Yehuda Elyasaf <30yehuda26@gmail.com>
Maintainer-email: Yehuda Elyasaf <30yehuda26@gmail.com>
Project-URL: Homepage, https://www.youtube.com/watch?v=dQw4w9WgXcQ
Classifier: License :: OSI Approved :: MIT License
Classifier: Operating System :: OS Independent
License-File: LICENSE
